django_uuid47/__init__.py
django_uuid47/apps.py
django_uuid47/fields.py
django_uuid47/forms.py
django_uuid47/py.typed
django_uuid47-0.1.0.dist-info/licenses/LICENSE
django_uuid47-0.1.0.dist-info/METADATA
django_uuid47-0.1.0.dist-info/WHEEL
django_uuid47-0.1.0.dist-info/top_level.txt
django_uuid47-0.1.0.dist-info/RECORD
