Metadata-Version: 2.4
Name: django-uuid47
Version: 0.1.0
Summary: Django UUID47 field and utilities.
Author-email: Markus Holtermann <info@markusholtermann.eu>
License-Expression: MIT
Project-URL: Changelog, https://github.com/MarkusH/django-uuid47/blob/main/CHANGELOG.rst
Project-URL: Funding, https://github.com/sponsors/MarkusH/
Project-URL: Repository, https://github.com/MarkusH/django-uuid47
Keywords: Django
Classifier: Development Status :: 5 - Production/Stable
Classifier: Framework :: Django :: 5.2
Classifier: Framework :: Django :: 6.0
Classifier: Framework :: IPython
Classifier: Intended Audience :: Developers
Classifier: Natural Language :: English
Classifier: Operating System :: OS Independent
Classifier: Programming Language :: Python :: 3 :: Only
Classifier: Programming Language :: Python :: 3.14
Classifier: Programming Language :: Python :: Implementation :: CPython
Classifier: Typing :: Typed
Requires-Python: >=3.14
License-File: LICENSE
Requires-Dist: django>=4.2
Requires-Dist: python-uuidv47>=1.0.7
Dynamic: license-file
